raft/__init__.py
raft/config.py
raft/group.py
raft/log.py
raft/master.py
raft/node.py
raft/rpc.py
raft/slave.py
test/__init__.py
test/client.py
test/test_master.py
test/test_slave.py
raft_python-0.1.0.dist-info/LICENSE
raft_python-0.1.0.dist-info/METADATA
raft_python-0.1.0.dist-info/WHEEL
raft_python-0.1.0.dist-info/top_level.txt
raft_python-0.1.0.dist-info/RECORD
